Metadata-Version: 2.4
Name: pyln-proto
Version: 25.12
Summary: This package implements some of the Lightning Network protocol in pure python. It is intended for protocol testing and some minor tooling only. It is not deemed secure enough to handle any amount of real funds (you have been warned!).
Author-email: Christian Decker <decker.christian@gmail.com>
License: BSD-MIT
Requires-Python: <4.0,>=3.9.2
Requires-Dist: base58>=2.1.1
Requires-Dist: bitstring>=4.3.0
Requires-Dist: coincurve==20.0.0
Requires-Dist: cryptography>=46
Requires-Dist: pysocks>=1
